example_package_n_zupp/__init__.py
example_package_n_zupp/ex2.py
example_package_n_zupp/example.py
example_package_n_zupp-0.1.5.dist-info/LICENSE
example_package_n_zupp-0.1.5.dist-info/WHEEL
example_package_n_zupp-0.1.5.dist-info/METADATA
example_package_n_zupp-0.1.5.dist-info/RECORD
