Metadata-Version: 2.3
Name: example_package_n_zupp
Version: 0.1.5
Summary: An example package for learning Python packaging.
Classifier: License :: OSI Approved :: MIT License
